{
  "global/palette": {
    "neutral": {
      "0": {
        "value": "#000000",
        "type": "color"
      },
      "10": {
        "value": "#1A1C18",
        "type": "color"
      },
      "20": {
        "value": "#2F312D",
        "type": "color"
      },
      "30": {
        "value": "#464743",
        "type": "color"
      },
      "40": {
        "value": "#5D5F5A",
        "type": "color"
      },
      "50": {
        "value": "#767872",
        "type": "color"
      },
      "60": {
        "value": "#90918B",
        "type": "color"
      },
      "70": {
        "value": "#ABACA6",
        "type": "color"
      },
      "80": {
        "value": "#C6C7C0",
        "type": "color"
      },
      "90": {
        "value": "#E3E3DC",
        "type": "color"
      },
      "95": {
        "value": "#F1F1EA",
        "type": "color"
      },
      "99": {
        "value": "#F1F1EA",
        "type": "color"
      },
      "100": {
        "value": "#FFFFFF",
        "type": "color"
      }
    },
    "primary": {
      "0": {
        "value": "#000000",
        "type": "color"
      },
      "10": {
        "value": "#052100",
        "type": "color"
      },
      "20": {
        "value": "#0E3900",
        "type": "color"
      },
      "30": {
        "value": "#185200",
        "type": "color"
      },
      "40": {
        "value": "#226D00",
        "type": "color"
      },
      "50": {
        "value": "#2D8900",
        "type": "color"
      },
      "60": {
        "value": "#44A51C",
        "type": "color"
      },
      "70": {
        "value": "#5FC138",
        "type": "color"
      },
      "80": {
        "value": "#7ADE51",
        "type": "color"
      },
      "90": {
        "value": "#95FB6B",
        "type": "color"
      },
      "95": {
        "value": "#CCFFB2",
        "type": "color"
      },
      "99": {
        "value": "#F7FFED",
        "type": "color"
      },
      "100": {
        "value": "#FFFFFF",
        "type": "color"
      }
    },
    "info": {
      "0": {
        "value": "#000000",
        "type": "color"
      },
      "10": {
        "value": "#001944",
        "type": "color"
      },
      "20": {
        "value": "#002D6D",
        "type": "color"
      },
      "30": {
        "value": "#004299",
        "type": "color"
      },
      "40": {
        "value": "#0059C8",
        "type": "color"
      },
      "50": {
        "value": "#2471ED",
        "type": "color"
      },
      "60": {
        "value": "#538DFF",
        "type": "color"
      },
      "70": {
        "value": "#84AAFF",
        "type": "color"
      },
      "80": {
        "value": "#AFC6FF",
        "type": "color"
      },
      "90": {
        "value": "#D9E2FF",
        "type": "color"
      },
      "95": {
        "value": "#EDF0FF",
        "type": "color"
      },
      "99": {
        "value": "#F5F7FF",
        "type": "color"
      },
      "100": {
        "value": "#FFFFFF",
        "type": "color"
      }
    },
    "success": {
      "0": {
        "value": "#000000",
        "type": "color"
      },
      "10": {
        "value": "#002108",
        "type": "color"
      },
      "20": {
        "value": "#003913",
        "type": "color"
      },
      "30": {
        "value": "#00531E",
        "type": "color"
      },
      "40": {
        "value": "#006E2B",
        "type": "color"
      },
      "50": {
        "value": "#20893E",
        "type": "color"
      },
      "60": {
        "value": "#40A455",
        "type": "color"
      },
      "70": {
        "value": "#5CBF6D",
        "type": "color"
      },
      "80": {
        "value": "#85DF92",
        "type": "color"
      },
      "90": {
        "value": "#BEF4C4",
        "type": "color"
      },
      "95": {
        "value": "#DBFFDC",
        "type": "color"
      },
      "99": {
        "value": "#F6FFF1",
        "type": "color"
      },
      "100": {
        "value": "#FFFFFF",
        "type": "color"
      }
    },
    "warning": {
      "0": {
        "value": "#000000",
        "type": "color"
      },
      "10": {
        "value": "#2C1700",
        "type": "color"
      },
      "20": {
        "value": "#492900",
        "type": "color"
      },
      "30": {
        "value": "#683D00",
        "type": "color"
      },
      "40": {
        "value": "#895200",
        "type": "color"
      },
      "50": {
        "value": "#AB6700",
        "type": "color"
      },
      "60": {
        "value": "#CC7F19",
        "type": "color"
      },
      "70": {
        "value": "#EB9934",
        "type": "color"
      },
      "80": {
        "value": "#FFB86A",
        "type": "color"
      },
      "90": {
        "value": "#FFDCBC",
        "type": "color"
      },
      "95": {
        "value": "#FFEEE0",
        "type": "color"
      },
      "99": {
        "value": "#FFFBFF",
        "type": "color"
      },
      "100": {
        "value": "#FFFFFF",
        "type": "color"
      }
    },
    "danger": {
      "0": {
        "value": "#000000",
        "type": "color"
      },
      "10": {
        "value": "#400009",
        "type": "color"
      },
      "20": {
        "value": "#680015",
        "type": "color"
      },
      "30": {
        "value": "#920022",
        "type": "color"
      },
      "40": {
        "value": "#BF002F",
        "type": "color"
      },
      "50": {
        "value": "#E42944",
        "type": "color"
      },
      "60": {
        "value": "#FF5261",
        "type": "color"
      },
      "70": {
        "value": "#FF888B",
        "type": "color"
      },
      "80": {
        "value": "#FFB3B3",
        "type": "color"
      },
      "90": {
        "value": "#FFDAD9",
        "type": "color"
      },
      "95": {
        "value": "#FFEDEC",
        "type": "color"
      },
      "99": {
        "value": "#FFFBFF",
        "type": "color"
      },
      "100": {
        "value": "#FFFFFF",
        "type": "color"
      }
    }
  },
  "theme/light": {},
  "theme/dark": {},
  "$themes": [
    {
      "id": "a8e85325af21cedfbc59f07e1b09906595276c10",
      "name": "Light",
      "$figmaStyleReferences": {},
      "selectedTokenSets": {
        "global/palette": "enabled"
      },
      "$figmaCollectionId": "VariableCollectionId:621:144",
      "$figmaModeId": "621:0",
      "$figmaVariableReferences": {
        "neutral.0": "f934b316de95736776521598b58629ac88b14bb7"
      },
      "group": "Theme"
    },
    {
      "id": "49edb569fa0aa0a59469c46c50cbf5421361fd7a",
      "name": "Dark",
      "$figmaStyleReferences": {},
      "selectedTokenSets": {
        "global/palette": "enabled"
      },
      "$figmaCollectionId": "VariableCollectionId:621:146",
      "$figmaModeId": "621:1",
      "$figmaVariableReferences": {
        "neutral.0": "cdcb7e319355e6a1fa453f3bf644424d4ceed9b5"
      },
      "group": "Theme"
    }
  ],
  "$metadata": {
    "tokenSetOrder": [
      "global/palette",
      "theme/light",
      "theme/dark"
    ]
  }
}